personalinfo/__init__.py
personalinfo/bank.py
personalinfo/contact.py
personalinfo/core.py
personalinfo/education.py
personalinfo/family.py
personalinfo/professional.py
personalinfo/template.html
personalinfo/vehicle.py
personalinfo-0.1.20.dist-info/licenses/LICENSE
personalinfo-0.1.20.dist-info/METADATA
personalinfo-0.1.20.dist-info/WHEEL
personalinfo-0.1.20.dist-info/top_level.txt
personalinfo-0.1.20.dist-info/RECORD
