Metadata-Version: 2.4
Name: personalinfo
Version: 0.1.20
Summary: A Python package for managing, exporting, and organizing personal information, including contact, family, education, professional, and more, with beautiful export options.
Author: prabaharan
Author-email: prabaharanpython@gmail.com
License: MIT
License-File: LICENSE
Provides-Extra: dev
Requires-Dist: pytest; extra == "dev"
Dynamic: license-file
